{"type":"FeatureCollection","features":[{"type":"Feature","geometry":{"type":"Point","coordinates":[-117.415277777778,47.6627777777778,0]},"properties":{"name":"Upper Falls Dam","description":"<br>Source: Wikipedia article <a href=\"https://en.wikipedia.org/wiki/List_of_dams_in_the_Columbia_River_watershed#cite_ref-UpperFalls_230-1\">List of dams in the Columbia River watershed</a>"}},{"type":"Feature","geometry":{"type":"Point","coordinates":[-117.425277777778,47.6616666666667,0]},"properties":{"name":"Monroe Street Dam","description":"<br>Source: Wikipedia article <a href=\"https://en.wikipedia.org/wiki/List_of_dams_in_the_Columbia_River_watershed#cite_ref-Monroe_231-1\">List of dams in the Columbia River watershed</a>"}},{"type":"Feature","geometry":{"type":"Point","coordinates":[-117.543888888889,47.775,0]},"properties":{"name":"Nine Mile Dam","description":"<br>Source: Wikipedia article <a href=\"https://en.wikipedia.org/wiki/List_of_dams_in_the_Columbia_River_watershed#cite_ref-NineMile_232-1\">List of dams in the Columbia River watershed</a>"}}]}